chatbotmaker/__init__.py
chatbotmaker/bot.py
chatbotmaker/database.py
chatbotmaker/dispatcher.py
chatbotmaker/extended_user.py
chatbotmaker/messenger.py
chatbotmaker/defaults/__init__.py
chatbotmaker/defaults/dev.py
chatbotmaker/defaults/facebook.py
chatbotmaker/defaults/simple_database.py
chatbotmaker-0.0.13.dist-info/LICENSE
chatbotmaker-0.0.13.dist-info/METADATA
chatbotmaker-0.0.13.dist-info/WHEEL
chatbotmaker-0.0.13.dist-info/top_level.txt
chatbotmaker-0.0.13.dist-info/RECORD
