Metadata-Version: 2.1
Name: chatbotmaker
Version: 0.0.13
Summary: This package automates the process of bot creation
Home-page: https://github.com/Dominique57/ChatBotMaker
Author: Dominique MICHEL
Author-email: dominique.michel@epita.fr
License: UNKNOWN
Platform: UNKNOWN
Classifier: Programming Language :: Python :: 3
Classifier: Operating System :: OS Independent
Requires-Python: >=3.6
Requires-Dist: sqlalchemy
